my_lattice_graph/__init__.py
my_lattice_graph/nodes.py
my_lattice_graph/pipeline.py
psdesign-0.1.0.dist-info/LICENSE
psdesign-0.1.0.dist-info/METADATA
psdesign-0.1.0.dist-info/WHEEL
psdesign-0.1.0.dist-info/top_level.txt
psdesign-0.1.0.dist-info/RECORD
