Metadata-Version: 2.2
Name: psdesign
Version: 0.1.0
Summary: A node-based library for porous structures design based on networks. 
Author-email: Avez Shaikh <aas6636@psu.edu>
License: MIT License
Project-URL: Homepage, https://github.com/avez1999/Design-of-porous-structures
Project-URL: Repository, https://github.com/avez1999/Design-of-porous-structures
Keywords: cadquery,lattice,node-graph,procedural-modeling
Classifier: Programming Language :: Python :: 3
Classifier: License :: OSI Approved :: MIT License
Classifier: Operating System :: OS Independent
Requires-Python: >=3.7
License-File: LICENSE
Requires-Dist: cadquery>=2.1.0
Requires-Dist: numpy>=1.19.0
